developer_disk_image/__init__.py
developer_disk_image/_version.py
developer_disk_image/exceptions.py
developer_disk_image/repo.py
developer_disk_image-0.1.0.dist-info/METADATA
developer_disk_image-0.1.0.dist-info/WHEEL
developer_disk_image-0.1.0.dist-info/entry_points.txt
developer_disk_image-0.1.0.dist-info/top_level.txt
developer_disk_image-0.1.0.dist-info/RECORD
